pancaik/__init__.py
pancaik/agents/TwitterAgent.py
pancaik/agents/TwitterAgent.yaml
pancaik/core/__init__.py
pancaik/core/agent.py
pancaik/core/config.py
pancaik/core/data_handler.py
pancaik/core/db.py
pancaik/core/task_handler.py
pancaik/core/task_runner.py
pancaik/services/__init__.py
pancaik/services/twitter/__init__.py
pancaik/services/twitter/api.py
pancaik/services/twitter/client.py
pancaik/services/twitter/handlers.py
pancaik/services/twitter/models.py
pancaik/services/twitter/tools/__init__.py
pancaik/services/twitter/tools/content.py
pancaik/services/twitter/tools/indexing.py
pancaik/services/twitter/tools/interaction.py
pancaik/services/twitter/tools/publishing.py
pancaik/services/twitter/tools/replies.py
pancaik/services/twitter/tools/search.py
pancaik/tools/__init__.py
pancaik/tools/base.py
pancaik/tools/research.py
pancaik/tools/template.py
pancaik/tools/topics.py
pancaik/utils/__init__.py
pancaik/utils/ai_images.py
pancaik/utils/ai_router.py
pancaik/utils/json_parser.py
pancaik-0.1.2.dist-info/LICENSE
pancaik-0.1.2.dist-info/METADATA
pancaik-0.1.2.dist-info/WHEEL
pancaik-0.1.2.dist-info/RECORD
