Metadata-Version: 2.3
Name: pancaik
Version: 0.1.2
Summary: A framework for building intelligent agents that perform scheduled tasks and provide chat interfaces
License: MIT
Keywords: agents,automation,chatbot,scheduling,tasks
Author: jc_stack
Author-email: jc@ezenciel.com
Requires-Python: >=3.11,<4.0
Classifier: Development Status :: 4 - Beta
Classifier: Intended Audience :: Developers
Classifier: License :: OSI Approved :: MIT License
Classifier: Programming Language :: Python :: 3
Classifier: Programming Language :: Python :: 3.11
Classifier: Programming Language :: Python :: 3.12
Classifier: Programming Language :: Python :: 3.13
Classifier: Topic :: Software Development :: Libraries :: Application Frameworks
Classifier: Topic :: Software Development :: Libraries :: Python Modules
Requires-Dist: aiohttp (>=3.11.16,<4.0.0)
Requires-Dist: async-lru (>=2.0.5,<3.0.0)
Requires-Dist: croniter (>=6.0.0,<7.0.0)
Requires-Dist: dotenv (>=0.9.9,<0.10.0)
Requires-Dist: fastapi (>=0.115.12,<0.116.0)
Requires-Dist: langchain-core (>=0.3.51,<0.4.0)
Requires-Dist: loguru (>=0.7.3,<0.8.0)
Requires-Dist: mkdocs (>=1.6.1,<2.0.0)
Requires-Dist: mkdocs-material (>=9.6.11,<10.0.0)
Requires-Dist: motor (>=3.7.0,<4.0.0)
Requires-Dist: oauthlib (>=3.2.2,<4.0.0)
Requires-Dist: openai (>=1.72.0,<2.0.0)
Requires-Dist: pyyaml (>=6.0.2,<7.0.0)
Requires-Dist: tweepy (>=4.15.0,<5.0.0)
Requires-Dist: uvicorn (>=0.34.0,<0.35.0)
Project-URL: Documentation, https://jdorado.github.io/pancaik/
Project-URL: Homepage, https://github.com/jdorado/pancaik
Project-URL: Repository, https://github.com/jdorado/pancaik
